finalynx/__init__.py
finalynx/__main__.py
finalynx/__meta__.py
finalynx/analyzer/__init__.py
finalynx/analyzer/analyzer.py
finalynx/analyzer/asset_class.py
finalynx/analyzer/asset_subclass.py
finalynx/analyzer/envelopes.py
finalynx/analyzer/investment_state.py
finalynx/analyzer/lines.py
finalynx/assistant.py
finalynx/budget/__init__.py
finalynx/budget/_render.py
finalynx/budget/_review.py
finalynx/budget/budget.py
finalynx/budget/expense.py
finalynx/budget/source_base_expense.py
finalynx/budget/source_n26.py
finalynx/config.py
finalynx/console.py
finalynx/copilot/__init__.py
finalynx/copilot/copilot.py
finalynx/copilot/recommendations.py
finalynx/dashboard/__init__.py
finalynx/dashboard/dashboard.py
finalynx/fetch/__init__.py
finalynx/fetch/_source_template.py
finalynx/fetch/fetch.py
finalynx/fetch/fetch_line.py
finalynx/fetch/source_base.py
finalynx/fetch/source_base_line.py
finalynx/fetch/source_finary.py
finalynx/fetch/source_realt.py
finalynx/parse/__init__.py
finalynx/parse/json.py
finalynx/parse/parser.py
finalynx/portfolio/__init__.py
finalynx/portfolio/bucket.py
finalynx/portfolio/constants.py
finalynx/portfolio/envelope.py
finalynx/portfolio/folder.py
finalynx/portfolio/hierarchy.py
finalynx/portfolio/line.py
finalynx/portfolio/node.py
finalynx/portfolio/render.py
finalynx/portfolio/targets.py
finalynx/simulator/__init__.py
finalynx/simulator/actions.py
finalynx/simulator/events.py
finalynx/simulator/recurrence.py
finalynx/simulator/timeline.py
finalynx/theme.py
finalynx/usage.py
finalynx-1.23.0.dist-info/LICENSE
finalynx-1.23.0.dist-info/METADATA
finalynx-1.23.0.dist-info/WHEEL
finalynx-1.23.0.dist-info/RECORD
