Metadata-Version: 2.1
Name: finalynx
Version: 1.23.0
Summary: A command line investment assistant to organize your portfolio and simulate its future to reach your life goals.
License: GPLv3
Author: MadeInPierre
Author-email: pielaclau@gmail.com
Requires-Python: >=3.10,<4.0
Classifier: License :: Other/Proprietary License
Classifier: Programming Language :: Python :: 3
Classifier: Programming Language :: Python :: 3.10
Classifier: Programming Language :: Python :: 3.11
Requires-Dist: docopt (==0.6.2)
Requires-Dist: finary-uapi (>=0.1.4,<0.2.0)
Requires-Dist: gspread (>=5.10.0,<6.0.0)
Requires-Dist: html2image (>=2.0.3,<3.0.0)
Requires-Dist: iso18245 (>=1.2.0,<2.0.0)
Requires-Dist: n26 (>=3.3.1,<4.0.0)
Requires-Dist: nicegui (>=1.2.13,<2.0.0)
Requires-Dist: numpy (>=1.24.2,<2.0.0)
Requires-Dist: pytz (>=2023.3,<2024.0)
Requires-Dist: rich (==12.0.1)
Requires-Dist: unidecode (>=1.3.6,<2.0.0)
